pdf2textlib/__init__.py
pdf2textlib/pdflib.py
pdf2textlib-1.0.4.dist-info/LICENSE
pdf2textlib-1.0.4.dist-info/METADATA
pdf2textlib-1.0.4.dist-info/WHEEL
pdf2textlib-1.0.4.dist-info/top_level.txt
pdf2textlib-1.0.4.dist-info/RECORD
