Metadata-Version: 2.1
Name: pdf2textlib
Version: 1.0.4
Summary: A package to extract text from PDF
Home-page: https://github.com/FSOCIETY06/pdf2textlib
Author: Vedant Khairnar
Author-email: vedron007@gmail.com
License: UNKNOWN
Platform: UNKNOWN
Classifier: Programming Language :: Python :: 3
Classifier: License :: OSI Approved :: MIT License
Classifier: Operating System :: OS Independent
Requires-Python: >=3.5
